{
    "cpu_set": [
        1,
        2
    ],
    "memtable_size_set": [
        "16*1024*1024",
        "32*1024*1024",
        "64*1024*1024"
    ],
    "storage_paths": [
        {
            "path": "/media/jinghuan/rocksdb_nvme",
            "media_type": "NVMeSSD"
        },
        {
            "path": "/media/jinghuan/rocksdb_ssd",
            "media_type": "SATASSD"
        },
        {
            "path": "/media/jinghuan/rocksdb_hdd",
            "media_type": "SATAHDD"
        },
        {
            "path": "/media/jinghuan/rocksdb_pmem",
            "media_type": "PM"
        }
    ]
}